LICENSE.md
MANIFEST.in
README.rst
setup.py
momitcool/__init__.py
momitcool/cli.py
momitcool/coap.py
py_momit_cool_remote.egg-info/PKG-INFO
py_momit_cool_remote.egg-info/SOURCES.txt
py_momit_cool_remote.egg-info/dependency_links.txt
py_momit_cool_remote.egg-info/entry_points.txt
py_momit_cool_remote.egg-info/top_level.txt