Metadata-Version: 1.1
Name: py-momit-cool-remote
Version: 1.1
Summary: Library for remotely interfacing with the Momit Cool air conditioning controller.
Home-page: https://github.com/Photonios/py-momit-cool-remote
Author: Swen Kooij
Author-email: swenkooij@gmail.com
License: MIT License
Keywords: momit,cool,remote,control
Platform: UNKNOWN
Classifier: Intended Audience :: Developers
Classifier: License :: OSI Approved :: MIT License
Classifier: Operating System :: OS Independent
Classifier: Programming Language :: Python
Classifier: Programming Language :: Python :: 3.5
Classifier: Topic :: Internet :: WWW/HTTP
Classifier: Topic :: Internet :: WWW/HTTP :: Dynamic Content
